{
  "personal_price":["10 هزار","25 هزار","50 هزار","70 هزار","100 هزار","150 هزار","300 هزار","800 هزار","1 میلیون","5 میلیون","10 میلیون","15 میلیون","50 میلیون"],
  
  "type_araiesh":["لوازم آرایشی و زیبایی","لوازم طبی و درمانی","لوازم برقی شخصی","مراقبتی پوست و مو","عطر و ادکلن","قرص و ترکیبات گیاهی","غیره"],
  "jens_adalt":["زنانه","مردانه","زنانه و مردانه"],
  "jens_child": ["دخترانه", "پسرانه", "پسرانه و دخترانه"],
  "type_kif": ["کیف", "کفش", "کمربند", "ست"],
  "type_clothes": [
      "مانتو",
      "شال و روسری",
      "تیشرت",
      "بلوز و شومیز",
      "شلوار",
      "ژاکت و پلیور",
      "لباس مجلسی",
      "لباس عروس",
      "کت و شلوار",
      "لباس زیر",
      "کاپشن،پالتو، بارانی",
      "لباس ورزشی",
      "جوراب،ساق،دستکش",
      "کلاه",
      "سایر"
    ],
  "type_watch": ["آنالوگ", "دیجیتال", "هوشمند", "سایر"],
  "type_javaher": [
    "انگشتر",
    "گوشواره",
    "دستبند",
    "زنجیر و گردن بند",
    "پابند",
    "ست و نیم ست",
    "غیره"
  ],
  "type_badalijat": [
    "انگشتر",
    "گوشواره",
    "دستبند",
    "زنجیر و گردن بند",
    "پابند",
    "ست و نیم ست",
    "غیره"
  ],
  "jenskala_javaher": ["طلا", "نقره", "آبکاری طلا", "سنگ قیمتی", "غیره"],
  "darRagMokhtalef": ["دارد", "ندارد"],
  "tolidi":["ایرانی","خارجی"]
}